consulta_cep/__init__.py
consulta_cep/__main__.py
consulta_cep/engine_cep.py
consulta_cep/servicos.py
consulta_cep/util.py
tests/__init__.py
tests/test_consulta_cep.py
consulta_cep-0.2.0.dist-info/LICENSE
consulta_cep-0.2.0.dist-info/METADATA
consulta_cep-0.2.0.dist-info/WHEEL
consulta_cep-0.2.0.dist-info/entry_points.txt
consulta_cep-0.2.0.dist-info/top_level.txt
consulta_cep-0.2.0.dist-info/RECORD
