Metadata-Version: 2.1
Name: consulta_cep
Version: 0.2.0
Summary: Biblioteca para consulta de endereços a partir de CEP usando serviços variados.
Home-page: https://github.com/andreydani/consulta_cep
Author: Andrey Sant'Anna
Author-email: andreysantanna@gmail.com
Classifier: Programming Language :: Python :: 3
Classifier: License :: OSI Approved :: MIT License
Classifier: Operating System :: OS Independent
Requires-Python: >=3.6
License-File: LICENSE
Requires-Dist: requests
